LICENSE
MANIFEST.in
README.md
setup.py
gibson/.gitignore
gibson/__init__.py
gibson.egg-info/PKG-INFO
gibson.egg-info/SOURCES.txt
gibson.egg-info/dependency_links.txt
gibson.egg-info/entry_points.txt
gibson.egg-info/not-zip-safe
gibson.egg-info/requires.txt
gibson.egg-info/top_level.txt
gibson/assets/__init__.py
gibson/assets/assets_actions.py
gibson/assets/assets_manager.py
gibson/core/.gitignore
gibson/core/CMakeLists.txt
gibson/core/__init__.py
gibson/core/channels/.gitignore
gibson/core/channels/CMakeLists.txt
gibson/core/channels/FindFreeImage.cmake
gibson/core/channels/FindFreeImagePlus.cmake
gibson/core/channels/README.md
gibson/core/channels/__init__.py
gibson/core/channels/depth_render.py
gibson/core/channels/parse_pose_rotation.py
gibson/core/channels/archive/compare_img.py
gibson/core/channels/assimp/.clang-format
gibson/core/channels/assimp/.coveralls.yml
gibson/core/channels/assimp/.editorconfig
gibson/core/channels/assimp/.git
gibson/core/channels/assimp/.gitattributes
gibson/core/channels/assimp/.gitignore
gibson/core/channels/assimp/.travis.sh
gibson/core/channels/assimp/.travis.yml
gibson/core/channels/assimp/BUILDBINARIES_EXAMPLE.bat
gibson/core/channels/assimp/Build.md
gibson/core/channels/assimp/CHANGES
gibson/core/channels/assimp/CMakeLists.txt
gibson/core/channels/assimp/CONTRIBUTING.md
gibson/core/channels/assimp/CREDITS
gibson/core/channels/assimp/CodeConventions.md
gibson/core/channels/assimp/Dockerfile
gibson/core/channels/assimp/INSTALL
gibson/core/channels/assimp/LICENSE
gibson/core/channels/assimp/README
gibson/core/channels/assimp/Readme.md
gibson/core/channels/assimp/assimp.pc.in
gibson/core/channels/assimp/revision.h.in
gibson/core/channels/assimp/.github/FUNDING.yml
gibson/core/channels/assimp/.github/ISSUE_TEMPLATE/bug_report.md
gibson/core/channels/assimp/.github/ISSUE_TEMPLATE/feature_request.md
gibson/core/channels/assimp/.github/workflows/ccpp.yml
gibson/core/channels/assimp/.github/workflows/sanitizer.yml
gibson/core/channels/assimp/cmake/HunterGate.cmake
gibson/core/channels/assimp/cmake/assimp-hunter-config.cmake.in
gibson/core/channels/assimp/cmake/assimp-plain-config.cmake.in
