Metadata-Version: 2.1
Name: gibson
Version: 1.0.3
Summary: Real Environment Developed by Stanford University
Home-page: https://github.com/micheleantonazzi/GibsonEnv
Author: Michele Antonazzi
License: UNKNOWN
Platform: UNKNOWN
Classifier: License :: OSI Approved :: MIT License
Classifier: Programming Language :: Python :: 3.6
Classifier: Programming Language :: Python :: 3.7
Classifier: Programming Language :: Python :: 3.8
Classifier: Programming Language :: Python :: 3.9
Classifier: Programming Language :: Python :: 3.10
Requires-Python: >2.7, !=3.0.*, !=3.1.*, !=3.2.*, !=3.3.*, !=3.4.*, !=3.5.*, < 4
